halsim_ds_socket/__init__.py
halsim_ds_socket/main.py
halsim_ds_socket/py.typed
halsim_ds_socket/version.py
halsim_ds_socket/lib/libhalsim_ds_socket.so
robotpy_halsim_ds_socket-2026.2.1.dist-info/METADATA
robotpy_halsim_ds_socket-2026.2.1.dist-info/WHEEL
robotpy_halsim_ds_socket-2026.2.1.dist-info/entry_points.txt
robotpy_halsim_ds_socket-2026.2.1.dist-info/RECORD
