Metadata-Version: 2.4
Name: robotpy-halsim-ds-socket
Version: 2026.2.1
Summary: WPILib simulator DS Socket Extension
Author-email: RobotPy Development Team <robotpy@googlegroups.com>
License-Expression: BSD-3-Clause
Requires-Dist: robotpy-native-wpihal==2026.2.1
Requires-Dist: robotpy-native-wpinet==2026.2.1
